feincms_banners/__init__.py
feincms_banners/admin.py
feincms_banners/contents.py
feincms_banners/models.py
feincms_banners/urls.py
feincms_banners/views.py
feincms_banners/migrations/0001_initial.py
feincms_banners/migrations/__init__.py
feincms_banners/templates/content/banner/box.html
feincms_banners/templates/content/banner/default.html
feincms_banners/templates/content/banner/leaderboard.html
feincms_banners/templates/content/banner/skyscraper.html
feincms_banners-1.3.0.dist-info/DESCRIPTION.rst
feincms_banners-1.3.0.dist-info/METADATA
feincms_banners-1.3.0.dist-info/RECORD
feincms_banners-1.3.0.dist-info/WHEEL
feincms_banners-1.3.0.dist-info/metadata.json
feincms_banners-1.3.0.dist-info/top_level.txt
