Metadata-Version: 2.0
Name: feincms-banners
Version: 1.3.0
Summary: A simple banner system with views and clicks for FeinCMS.
Home-page: https://github.com/matthiask/feincms-banners/
Author: Matthias Kestenholz
Author-email: mk@406.ch
License: BSD License
Platform: OS Independent
Classifier: Environment :: Web Environment
Classifier: Framework :: Django
Classifier: Intended Audience :: Developers
Classifier: License :: OSI Approved :: BSD License
Classifier: Operating System :: OS Independent
Classifier: Programming Language :: Python
Classifier: Programming Language :: Python :: 2
Classifier: Programming Language :: Python :: 2.6
Classifier: Programming Language :: Python :: 2.7
Classifier: Programming Language :: Python :: 3
Classifier: Programming Language :: Python :: 3.2
Classifier: Programming Language :: Python :: 3.3
Classifier: Topic :: Internet :: WWW/HTTP :: Dynamic Content
Classifier: Topic :: Software Development
Requires-Dist: Django (>=1.4.2)
Requires-Dist: FeinCMS (>=1.6)
